src/alu/brent_kung_adder.vhd
------------------------------------------------------------
-- Title:       Brent-Kung-Adder
-- Description: 
-- Author:      Aaron Moser
-- Date:        20.05.2019
------------------------------------------------------------

library ieee;
use ieee.std_logic_1164.all;
use ieee.numeric_std.all;

entity brent_kung_adder is
  port
    (
      i_op1 : in std_logic_vector(15 downto 0);
      i_op2   : in  std_logic_vector(15 downto 0);
      i_c     : in  std_logic;
      o_res   : out std_logic_vector(15 downto 0);
      o_flags : out std_logic_vector(3 downto 0)
    );
end entity;

architecture behaviour of brent_kung_adder is

  constant stages : natural := 8;
  constant ct_stages : natural := 5;
  constant ict_stages : natural := 3;

  type t_tree is array(15 downto 0, stages-1 downto 0) of std_logic_vector(1 downto 0);
  
  signal carry_tree : t_tree;
  signal g_vec : std_logic_vector(15 downto 0);
  signal p_vec : std_logic_vector(15 downto 0);
  signal sum   : std_logic_vector(15 downto 0);

  signal add_z : std_logic;
  signal add_f : std_logic;
  signal add_c : std_logic;
  signal add_n : std_logic;

  function circ_op(op1 : in std_logic_vector(1 downto 0);
                   op2 : in std_logic_vector(1 downto 0)) return std_logic_vector is
    variable tmp1 : std_logic;
    variable tmp2 : std_logic;
    variable res : std_logic_vector(1 downto 0);
  begin
    tmp1 := op1(1) or (op1(0) and op2(1));
    tmp2 := op1(0) and op2(0);
    res := tmp1 & tmp2;
    return res;
  end function;

begin

  carry_proc : process(all)
  begin
    g_vec(0) <= (i_op1(0) and i_op2(0)) or (i_c and (i_op1(0) xor i_op2(0)));
    p_vec(0) <= i_op1(0) xor i_op2(0) xor i_c;
    for i in 1 to 15 loop
      g_vec(i) <= i_op1(i) and i_op2(i);
      p_vec(i) <= i_op1(i) xor i_op2(i);
    end loop;

    -- Carry Tree
    for k in 0 to ct_stages-1 loop
      for i in 0 to 15 loop
        -- Leaves
        if k = 0 then
          carry_tree(i,0) <= g_vec(i) & p_vec(i);
        else
          if (i mod 2**k = 2**k-1) then
            if 2**k-1 >= 0 then
              carry_tree(i,k) <= circ_op(carry_tree(i,k-1), carry_tree(i-2**k+1,k-1));
            else
              carry_tree(i,k) <= carry_tree(i,k-1);
            end if;
          else
            carry_tree(i,k) <= carry_tree(i,k-1);
          end if;
        end if;
      end loop;
    end loop;

    -- Inverse Carry Tree
    for k in ct_stages to stages-1 loop
      for i in 0 to 15 loop
        if ((i-2**(stages-k-1)) mod 2**(stages-k) = 2**(stages-k)-1) then
          if i >= 2**(stages-k-1) then
            carry_tree(i,k) <= circ_op(carry_tree(i,k-1), carry_tree(i-2**(stages-k-1),k-1));
          else
            carry_tree(i,k) <= carry_tree(i,k-1);
          end if;
        else
          carry_tree(i,k) <= carry_tree(i,k-1);
        end if;
      end loop;
    end loop;

  end process;

  sum_proc : process(all)
  begin
    sum(0) <= p_vec(0);
    for i in 1 to 15 loop
      sum(i) <= p_vec(i) xor carry_tree(i-1,stages-1)(1);
    end loop;
  end process;

  add_z <= '1' when sum = "0000000000000000" else '0';
  add_f <= '1' when (i_op1(15) and i_op2(15) and not sum(15)) or
           (not i_op1(15) and not i_op2(15) and sum(15)) else '0';
  add_n <= '1' when sum(15) = '1' else '0';
  add_c <= carry_tree(15,stages-1)(1);

  o_flags <= add_z & add_f & add_c & add_n;
  o_res <= sum;
end architecture;

tests/brent_kung_adder_tb.vhd
library ieee;
use ieee.std_logic_1164.all;

entity brent_kung_adder_tb is
end entity;

architecture behaviour of brent_kung_adder_tb is
  component brent_kung_adder is
    port
      (
        i_op1, i_op2  : in  std_logic_vector(15 downto 0);
        i_c           : in  std_logic;
        o_res         : out std_logic_vector(15 downto 0);
        o_flags       : out std_logic_vector(3 downto 0)
        );
  end component;

  signal opa_tb, opb_tb, eo_tb : std_logic_vector(15 downto 0);
  signal ci_tb                 : std_logic;
  signal flags_tb              : std_logic_vector(3 downto 0);
begin
  dut : brent_kung_adder port map
    (
      i_op1   => opa_tb,
      i_op2   => opb_tb,
      i_c     => ci_tb,
      o_res   => eo_tb,
      o_flags => flags_tb
      );

  stim_proc : process
    type pattern_type is record
      a, b  : std_logic_vector(15 downto 0);
      c     : std_logic;
      e     : std_logic_vector(15 downto 0);
      flags : std_logic_vector(3 downto 0);
    end record;

    type pattern_array is array(natural range <>) of pattern_type;
    constant patterns : pattern_array :=
      (("0000000000000000", "0000000000000000", '0', "0000000000000000", "1000"),
       ("0000000000000001", "0000000000000001", '0', "0000000000000010", "0000"),
       ("0000000000000001", "0000000000000001", '1', "0000000000000011", "0000"),
       ("1111111111111100", "0000000000000011", '0', "1111111111111111", "0001"),
       ("1010101010101010", "0101010101010101", '1', "0000000000000000", "1010"),
       ("0001000010001011", "0100001000000100", '1', "0101001010010000", "0000"),
       ("0001000010001011", "0100001000000100", '0', "0101001010001111", "0000"),
       ("0000100110010000", "1100000000000011", '0', "1100100110010011", "0001"),
       ("0000000000001111", "0000000000001111", '0', "0000000000011110", "0000"),
       ("0000000011111111", "0000000011111111", '1', "0000000111111111", "0000"));

  begin
    for i in patterns'range loop
      opa_tb <= patterns(i).a;
      opb_tb <= patterns(i).b;
      ci_tb  <= patterns(i).c;

      wait for 5 ns;
      assert eo_tb = patterns(i).e report "bad sum value" severity error;
      assert flags_tb = patterns(i).flags report "bad flag value" severity error;
    end loop;

    assert false report "Brent-Kung Adder testbench finished" severity note;
    wait;
  end process;
end;

sim/brent_kung_adder_tb.vcd
$date
  Sun May 26 21:43:15 2019
$end
$version
  GHDL v0
$end
$timescale
  1 fs
$end
$scope module standard $end
$upscope $end
$scope module textio $end
$upscope $end
$scope module std_logic_1164 $end
$upscope $end
$scope module numeric_std $end
$upscope $end
$scope module brent_kung_adder_tb $end
$var reg 16 ! opa_tb[15:0] $end
$var reg 16 " opb_tb[15:0] $end
$var reg 16 # eo_tb[15:0] $end
$var reg 1 $ ci_tb $end
$var reg 4 % flags_tb[3:0] $end
$scope module dut $end
$var reg 16 & i_op1[15:0] $end
$var reg 16 ' i_op2[15:0] $end
$var reg 1 ( i_c $end
$var reg 16 ) o_res[15:0] $end
$var reg 4 * o_flags[3:0] $end
$comment carry_tree is not handled $end
$var reg 16 + g_vec[15:0] $end
$var reg 16 , p_vec[15:0] $end
$var reg 16 - sum[15:0] $end
$var reg 1 . add_z $end
$var reg 1 / add_f $end
$var reg 1 0 add_c $end
$var reg 1 1 add_n $end
$upscope $end
$upscope $end
$enddefinitions $end
#0
b0000000000000000 !
b0000000000000000 "
b0000000000000000 #
0$
b1000 %
b0000000000000000 &
b0000000000000000 '
0(
b0000000000000000 )
b1000 *
b0000000000000000 +
b0000000000000000 ,
b0000000000000000 -
1.
0/
00
01
#5000000
b0000000000000001 !
b0000000000000001 "
b0000000000000010 #
b0000 %
b0000000000000001 &
b0000000000000001 '
b0000000000000010 )
b0000 *
b0000000000000001 +
b0000000000000010 -
0.
#10000000
b0000000000000011 #
1$
1(
b0000000000000011 )
b0000000000000001 ,
b0000000000000011 -
#15000000
b1111111111111100 !
b0000000000000011 "
b1111111111111111 #
0$
b0001 %
b1111111111111100 &
b0000000000000011 '
0(
b1111111111111111 )
b0001 *
b0000000000000000 +
b1111111111111111 ,
b1111111111111111 -
11
#20000000
b1010101010101010 !
b0101010101010101 "
b0000000000000000 #
1$
b1010 %
b1010101010101010 &
b0101010101010101 '
1(
b0000000000000000 )
b1010 *
b0000000000000001 +
b1111111111111110 ,
b0000000000000000 -
1.
10
01
#25000000
b0001000010001011 !
b0100001000000100 "
b0101001010010000 #
b0000 %
b0001000010001011 &
b0100001000000100 '
b0101001010010000 )
b0000 *
b0101001010001110 ,
b0101001010010000 -
0.
0/
00
01
#30000000
b0101001010001111 #
0$
0(
b0101001010001111 )
b0000000000000000 +
b0101001010001111 ,
b0101001010001111 -
#35000000
b0000100110010000 !
b1100000000000011 "
b1100100110010011 #
b0001 %
b0000100110010000 &
b1100000000000011 '
b1100100110010011 )
b0001 *
b1100100110010011 ,
b1100100110010011 -
11
#40000000
b0000000000001111 !
b0000000000001111 "
b0000000000011110 #
b0000 %
b0000000000001111 &
b0000000000001111 '
b0000000000011110 )
b0000 *
b0000000000001111 +
b0000000000000000 ,
b0000000000011110 -
0.
0/
01
#45000000
b0000000011111111 !
b0000000011111111 "
b0000000111111111 #
1$
b0000000011111111 &
b0000000011111111 '
1(
b0000000111111111 )
b0000000011111111 +
b0000000000000001 ,
b0000000111111111 -
