src/alu/cl_full_adder.vhd
------------------------------------------------------------
-- Title:       Carry Lookahead Full Adder
-- Description: A simple carry lookahead full adder
-- Author:      Aaron Moser
-- Date:        10.01.2019
------------------------------------------------------------

library ieee;
use ieee.std_logic_1164.all;

entity cl_full_adder is
  port
    (
      i_op1 : in  std_logic;
      i_op2 : in  std_logic;
      i_c   : in  std_logic;
      o_res : out std_logic;            -- sum value
      o_g   : out std_logic;            -- generation value
      o_p   : out std_logic             -- propagation value
      );
end;

architecture behaviour of cl_full_adder is
begin
  o_res <= i_op1 xor i_op2 xor i_c;
  o_g <= i_op1 and i_op2;
  o_p <= i_op1 or i_op2;
end;

old_files/tests/cl_full_adder_tb.vhd
library ieee;
use ieee.std_logic_1164.all;

entity cl_full_adder_tb is
end entity;

architecture behaviour of cl_full_adder_tb is
  component cl_full_adder is
    port
      (
        i_op1 : in  std_logic;
        i_op2 : in  std_logic;
        i_c   : in  std_logic;
        o_res : out std_logic;
        o_g   : out std_logic;
        o_p   : out std_logic
        );
  end component;

  signal opa_tb, opb_tb, c_tb, e_tb, g_tb, p_tb : std_logic;

begin
  dut : cl_full_adder port map
    (
      i_op1 => opa_tb,
      i_op2 => opb_tb,
      i_c   => c_tb,
      o_res => e_tb,
      o_g   => g_tb,
      o_p   => p_tb
      );

  stim_proc : process
    type pattern_type is record
      a, b, c : std_logic;
      e, g, p : std_logic;
    end record;

    type pattern_array is array(natural range <>) of pattern_type;
    constant patterns : pattern_array :=
      (('0', '0', '0', '0', '0', '0'),
       ('0', '1', '0', '1', '0', '1'),
       ('1', '0', '0', '1', '0', '1'),
       ('1', '1', '0', '0', '1', '1'),
       ('0', '0', '1', '1', '0', '0'),
       ('0', '1', '1', '0', '0', '1'),
       ('1', '0', '1', '0', '0', '1'),
       ('1', '1', '1', '1', '1', '1'));

  begin
    for i in patterns'range loop
      opa_tb <= patterns(i).a;
      opb_tb <= patterns(i).b;
      c_tb   <= patterns(i).c;

      wait for 1 ns;
      assert e_tb = patterns(i).e report "bad sum value" severity error;
      assert g_tb = patterns(i).g report "bad gen value" severity error;
      assert p_tb = patterns(i).p report "bad prop value" severity error;
    end loop;

    assert false report "CL full adder testbench finished" severity note;
    wait;
  end process;
end architecture;

sim/cl_full_adder_tb.vcd
$date
  Sun May 19 20:32:17 2019
$end
$version
  GHDL v0
$end
$timescale
  1 fs
$end
$scope module standard $end
$upscope $end
$scope module textio $end
$upscope $end
$scope module std_logic_1164 $end
$upscope $end
$scope module cl_full_adder_tb $end
$var reg 1 ! opa_tb $end
$var reg 1 " opb_tb $end
$var reg 1 # c_tb $end
$var reg 1 $ e_tb $end
$var reg 1 % g_tb $end
$var reg 1 & p_tb $end
$scope module dut $end
$var reg 1 ' i_op1 $end
$var reg 1 ( i_op2 $end
$var reg 1 ) i_c $end
$var reg 1 * o_res $end
$var reg 1 + o_g $end
$var reg 1 , o_p $end
$upscope $end
$upscope $end
$enddefinitions $end
#0
0!
0"
0#
0$
0%
0&
0'
0(
0)
0*
0+
0,
#1000000
1"
1$
1&
1(
1*
1,
#2000000
1!
0"
1'
0(
#3000000
1"
0$
1%
1(
0*
1+
#4000000
0!
0"
1#
1$
0%
0&
0'
0(
1)
1*
0+
0,
#5000000
1"
0$
1&
1(
0*
1,
#6000000
1!
0"
1'
0(
#7000000
1"
1$
1%
1(
1*
1+
