src/alu/lu.vhd
-----------------------------------------------------------
-- An LU (logic unit) which is responsible for logical operations in the ALU.
-- Author: Aaron Moser
-- Date: 12.01.2019
-----------------------------------------------------------

library ieee;
use ieee.std_logic_1164.all;

entity lu is
  port
    (
      i_op1   : in  std_logic_vector(15 downto 0);
      i_op2   : in  std_logic_vector(15 downto 0);
      i_and   : in  std_logic;
      i_or    : in  std_logic;
      i_xor   : in  std_logic;
      i_not   : in  std_logic;
      o_res   : out std_logic_vector(15 downto 0);
      o_flags : out std_logic_vector(3 downto 0) -- Z F C N
      );
end entity;

architecture behaviour of lu is
  signal res : std_logic_vector(15 downto 0);
  signal lu_z : std_logic := '0';
  signal lu_f : std_logic := '0';
  signal lu_c : std_logic := '0';
  signal lu_n : std_logic := '0';
begin
  logic_proc : process(all)
  begin
    if i_and = '1' then
      for i in 0 to 15 loop
        res(i) <= i_op1(i) and i_op2(i);
      end loop;
    elsif i_or = '1' then
      for i in 0 to 15 loop
        res(i) <= i_op1(i) or i_op2(i);
      end loop;
    elsif i_xor = '1' then
      for i in 0 to 15 loop
        res(i) <= i_op1(i) xor i_op2(i);
      end loop;
    else
      for i in 0 to 15 loop
        res(i) <= not i_op1(i);
      end loop;
    end if;
  end process;

  lu_z     <= '1' when res = "0000000000000000" else '0';
  lu_n     <= '1' when res(15) = '1'            else '0';
  o_flags <= lu_z & lu_f & lu_c & lu_n;
  o_res   <= res;
end architecture;

tests/lu_tb.vhd
library ieee;
use ieee.std_logic_1164.all;

entity lu_tb is
end lu_tb;

architecture behaviour of lu_tb is
  component lu is
    port
      (
        i_op1   : in  std_logic_vector(15 downto 0);
        i_op2   : in  std_logic_vector(15 downto 0);
        i_and   : in  std_logic;
        i_or    : in  std_logic;
        i_xor   : in  std_logic;
        i_not   : in  std_logic;
        o_res   : out std_logic_vector(15 downto 0);
        o_flags : out std_logic_vector(3 downto 0)
        );
  end component;

  signal op1_tb, op2_tb, res_tb        : std_logic_vector(15 downto 0);
  signal flags_tb                : std_logic_vector(3 downto 0);
  signal and_tb, or_tb, xor_tb, not_tb : std_logic;

begin
  dut : lu port map
    (
      i_op1 => op1_tb,
      i_op2 => op2_tb,
      i_and => and_tb,
      i_or  => or_tb,
      i_xor => xor_tb,
      i_not => not_tb,
      o_res => res_tb,
      o_flags => flags_tb
      );

  stim_proc : process
    type pattern_type is record
      op1   : std_logic_vector(15 downto 0);
      op2   : std_logic_vector(15 downto 0);
      und   : std_logic;
      oder  : std_logic;
      xoder : std_logic;
      nicht : std_logic;
      res   : std_logic_vector(15 downto 0);
      flags : std_logic_vector(3 downto 0);
    end record;

    type pattern_array is array(natural range <>) of pattern_type;
    constant patterns : pattern_array :=
      -- AND
      (("0111001010010001", "0111100111100101", '1', '0', '0', '0', "0111000010000001", "0000"),
       ("1001001010100001", "1000010001010101", '1', '0', '0', '0', "1000000000000001", "0001"),
       ("0000000000000000", "0000000000000000", '1', '0', '0', '0', "0000000000000000", "1000"),
       ("1111111111111111", "1111111111111111", '1', '0', '0', '0', "1111111111111111", "0001"),
            
       ("1001001010100001", "1000010001010101", '0', '1', '0', '0', "1001011011110101", "0001"),
       ("1111111111111111", "0000000000000000", '0', '1', '0', '0', "1111111111111111", "0001"),
       ("0000000000000000", "0000000000000000", '0', '1', '0', '0', "0000000000000000", "1000"),
       ("1111111111111111", "1111111111111111", '0', '1', '0', '0', "1111111111111111", "0001"),
             
       ("0100100110011101", "0111001010110101", '0', '0', '1', '0', "0011101100101000", "0000"),
       ("1111111111111111", "0000000000000000", '0', '0', '1', '0', "1111111111111111", "0001"),
       ("0000000000000000", "0000000000000000", '0', '0', '1', '0', "0000000000000000", "1000"),
       ("1111111111111111", "1111111111111111", '0', '0', '1', '0', "0000000000000000", "1000"),
             
       ("0000000000000000", "0000000000000000", '0', '0', '0', '1', "1111111111111111", "0001"),
       ("1111111111111111", "0000000000000000", '0', '0', '0', '1', "0000000000000000", "1000"),
       ("0100100101000101", "0100110110000001", '0', '0', '0', '1', "1011011010111010", "0001"));

  begin
    for i in patterns'range loop
      op1_tb <= patterns(i).op1;
      op2_tb <= patterns(i).op2;
      and_tb <= patterns(i).und;
      or_tb  <= patterns(i).oder;
      xor_tb <= patterns(i).xoder;
      not_tb <= patterns(i).nicht;
      wait for 1 ns;
      assert res_tb = patterns(i).res report "bad result" severity error;
      assert flags_tb = patterns(i).flags report "bad flag value" severity error;
    end loop;

    assert false report "Logic unit testbench finished" severity note;
    wait;
  end process;
end architecture;

sim/lu_tb.vcd
$date
  Sun May 19 20:51:35 2019
$end
$version
  GHDL v0
$end
$timescale
  1 fs
$end
$scope module standard $end
$upscope $end
$scope module textio $end
$upscope $end
$scope module std_logic_1164 $end
$upscope $end
$scope module lu_tb $end
$var reg 16 ! op1_tb[15:0] $end
$var reg 16 " op2_tb[15:0] $end
$var reg 16 # res_tb[15:0] $end
$var reg 4 $ flags_tb[3:0] $end
$var reg 1 % and_tb $end
$var reg 1 & or_tb $end
$var reg 1 ' xor_tb $end
$var reg 1 ( not_tb $end
$scope module dut $end
$var reg 16 ) i_op1[15:0] $end
$var reg 16 * i_op2[15:0] $end
$var reg 1 + i_and $end
$var reg 1 , i_or $end
$var reg 1 - i_xor $end
$var reg 1 . i_not $end
$var reg 16 / o_res[15:0] $end
$var reg 4 0 o_flags[3:0] $end
$var reg 16 1 res[15:0] $end
$var reg 1 2 lu_z $end
$var reg 1 3 lu_f $end
$var reg 1 4 lu_c $end
$var reg 1 5 lu_n $end
$upscope $end
$upscope $end
$enddefinitions $end
#0
b0111001010010001 !
b0111100111100101 "
b0111000010000001 #
b0000 $
1%
0&
0'
0(
b0111001010010001 )
b0111100111100101 *
1+
0,
0-
0.
b0111000010000001 /
b0000 0
b0111000010000001 1
02
03
04
05
#1000000
b1001001010100001 !
b1000010001010101 "
b1000000000000001 #
b0001 $
b1001001010100001 )
b1000010001010101 *
b1000000000000001 /
b0001 0
b1000000000000001 1
15
#2000000
b0000000000000000 !
b0000000000000000 "
b0000000000000000 #
b1000 $
b0000000000000000 )
b0000000000000000 *
b0000000000000000 /
b1000 0
b0000000000000000 1
12
05
#3000000
b1111111111111111 !
b1111111111111111 "
b1111111111111111 #
b0001 $
b1111111111111111 )
b1111111111111111 *
b1111111111111111 /
b0001 0
b1111111111111111 1
02
15
#4000000
b1001001010100001 !
b1000010001010101 "
b1001011011110101 #
0%
1&
b1001001010100001 )
b1000010001010101 *
0+
1,
b1001011011110101 /
b1001011011110101 1
#5000000
b1111111111111111 !
b0000000000000000 "
b1111111111111111 #
b1111111111111111 )
b0000000000000000 *
b1111111111111111 /
b1111111111111111 1
#6000000
b0000000000000000 !
b0000000000000000 #
b1000 $
b0000000000000000 )
b0000000000000000 /
b1000 0
b0000000000000000 1
12
05
#7000000
b1111111111111111 !
b1111111111111111 "
b1111111111111111 #
b0001 $
b1111111111111111 )
b1111111111111111 *
b1111111111111111 /
b0001 0
b1111111111111111 1
02
15
#8000000
b0100100110011101 !
b0111001010110101 "
b0011101100101000 #
b0000 $
0&
1'
b0100100110011101 )
b0111001010110101 *
0,
1-
b0011101100101000 /
b0000 0
b0011101100101000 1
05
#9000000
b1111111111111111 !
b0000000000000000 "
b1111111111111111 #
b0001 $
b1111111111111111 )
b0000000000000000 *
b1111111111111111 /
b0001 0
b1111111111111111 1
15
#10000000
b0000000000000000 !
b0000000000000000 #
b1000 $
b0000000000000000 )
b0000000000000000 /
b1000 0
b0000000000000000 1
12
05
#11000000
b1111111111111111 !
b1111111111111111 "
b1111111111111111 )
b1111111111111111 *
#12000000
b0000000000000000 !
b0000000000000000 "
b1111111111111111 #
b0001 $
0'
1(
b0000000000000000 )
b0000000000000000 *
0-
1.
b1111111111111111 /
b0001 0
b1111111111111111 1
02
15
#13000000
b1111111111111111 !
b0000000000000000 #
b1000 $
b1111111111111111 )
b0000000000000000 /
b1000 0
b0000000000000000 1
12
05
#14000000
b0100100101000101 !
b0100110110000001 "
b1011011010111010 #
b0001 $
b0100100101000101 )
b0100110110000001 *
b1011011010111010 /
b0001 0
b1011011010111010 1
02
15
