src/alu/shifter.vhd
------------------------------------------------------------
-- Title:       Barrel Shifter
-- Description: A barrel shifter which is able to shift by a variable amount.
--              It consists of four layers of multiplexers, one for each bit
--              in the shifting value i_s.
-- Author:      Aaron Moser
-- Date:        14.01.2019
------------------------------------------------------------


library ieee;
use ieee.std_logic_1164.all;
use ieee.numeric_std.all;

-- Utility entity for the barrel shifter
entity mux is
  generic
    (
      width : natural := 1
      );
  port
    (
      i_sig0 : in  std_logic_vector(width-1 downto 0);
      i_sig1 : in  std_logic_vector(width-1 downto 0);
      i_sel  : in  std_logic;
      o_sig  : out std_logic_vector(width-1 downto 0)
      );
end entity;

architecture behaviour of mux is
begin
  o_sig <= i_sig0 when i_sel = '0' else
           i_sig1 when i_sel = '1';
end architecture;


-- Shifter
library ieee;
use ieee.std_logic_1164.all;
use ieee.numeric_std.all;

entity shifter is
  port
    (
      i_op    : in  std_logic_vector(15 downto 0);
      i_s     : in  std_logic_vector(3 downto 0);
      i_dir   : in  std_logic;            -- direction 1 left 0 right
      i_rot   : in  std_logic;            -- rotate
      i_ar    : in  std_logic;            -- arithmetic shift
      o_res   : out std_logic_vector(15 downto 0);  -- result
      o_flags : out std_logic_vector(3 downto 0)
      );

  function reverse_vector(a : in std_logic_vector)
    return std_logic_vector is variable res : std_logic_vector(a'range);
                               alias aa : std_logic_vector(a'reverse_range) is a;
  begin
    for i in aa'range loop
      res(i) := aa(i);
    end loop;
    return res;
  end function;

end entity;

architecture behaviour of shifter is
  component mux is
    generic
      (
        width : natural
        );
    port
      (
        i_sig0 : in  std_logic_vector(width-1 downto 0);
        i_sig1 : in  std_logic_vector(width-1 downto 0);
        i_sel  : in  std_logic;
        o_sig  : out std_logic_vector(width-1 downto 0)
        );
  end component;

  -- Reverse signals
  signal rev_0   : std_logic_vector(15 downto 0);
  signal rev_0_8 : std_logic_vector(7 downto 0);
  signal rev_0_4 : std_logic_vector(3 downto 0);
  signal rev_0_2 : std_logic_vector(1 downto 0);
  signal rev_1   : std_logic_vector(15 downto 0);

  -- Rotation signals
  signal rot_0 : std_logic_vector(15 downto 0);
  signal rot_1 : std_logic_vector(15 downto 0);
  signal rot_2 : std_logic_vector(15 downto 0);
  signal rot_3 : std_logic_vector(15 downto 0);

  -- Shifting signals
  signal s_l0 : std_logic_vector(15 downto 0);
  signal s_l1 : std_logic_vector(15 downto 0);
  signal s_l2 : std_logic_vector(15 downto 0);
  signal s_l3 : std_logic_vector(15 downto 0);

  -- Arithmetic shifting
  signal s        : std_logic := '0';
  signal s_2      : std_logic_vector(1 downto 0);
  signal s_4      : std_logic_vector(3 downto 0);
  signal s_8      : std_logic_vector(7 downto 0);
  signal sl       : std_logic := '0';
  signal sr       : std_logic := '0';
  signal sign_sig : std_logic := '0';
  signal adj_s_l3 : std_logic_vector(15 downto 0);

  -- Overflow detection
  signal of_mux_out0 : std_logic_vector(7 downto 0);
  signal of_mux_out1 : std_logic_vector(3 downto 0);
  signal of_mux_out2 : std_logic_vector(1 downto 0);
  signal of_mux_out3 : std_logic;

  signal xor_out0 : std_logic_vector(7 downto 0) := (others => '0');
  signal xor_out1 : std_logic_vector(3 downto 0) := (others => '0');
  signal xor_out2 : std_logic_vector(1 downto 0) := (others => '0');
  signal xor_out3 : std_logic                    := '0';

  signal of_tmp0 : std_logic := '0';
  signal of_tmp1 : std_logic := '0';
  signal of_tmp2 : std_logic := '0';
  signal of_tmp3 : std_logic := '0';

  -- Flags
  signal sh_z : std_logic := '0';
  signal sh_f : std_logic := '0';
  signal sh_c : std_logic := '0';
  signal sh_n : std_logic := '0';
begin
  s_8 <= (others => s);
  s_4 <= (others => s);
  s_2 <= (others => s);

  sr <= not i_dir and i_ar;
  sl <= i_dir and i_ar;

  rev_0_8 <= (others => rev_0(0));
  rev_0_4 <= (others => rev_0(0));
  rev_0_2 <= (others => rev_0(0));

  -- Generate Multiplexer layers
  -- Reverse the bit order for a right shift
  rev0_mux : mux
    generic map
    (
      width => 16
      )
    port map
    (
      i_sig0 => i_op,
      i_sig1 => reverse_vector(i_op),
      i_sel  => i_dir,
      o_sig  => rev_0
      );

  -- Arithmetic right shifting
  arith_mux : mux
    generic map
    (
      width => 1
      )
    port map
    (
      i_sig1(0) => rev_0(15),
      i_sig0(0) => '0',
      i_sel     => sr,
      o_sig(0)  => s
      );

  -- Zeroth rotation layer
  rot_l0_mux : mux
    generic map
    (
      width => 8
      )
    port map
    (
      i_sig0 => s_8,
      i_sig1 => rev_0(7 downto 0),
      i_sel  => i_rot,
      o_sig  => rot_0(15 downto 8)
      );

  rot_0(7 downto 0) <= rev_0(15 downto 8);

  -- 8-bit shift
  mux_8shift : mux
    generic map
    (
      width => 16
      )
    port map
    (
      i_sig0 => rev_0,
      i_sig1 => rot_0,
      i_sel  => i_s(3),
      o_sig  => s_l0
      );

  -- First rotation layer
  rot_l1_mux : mux
    generic map
    (
      width => 4
      )
    port map
    (
      i_sig0 => s_4,
      i_sig1 => s_l0(3 downto 0),
      i_sel  => i_rot,
      o_sig  => rot_1(15 downto 12)
      );

  rot_1(11 downto 0) <= s_l0(15 downto 4);

  -- 4-bit shift
  mux_4shift : mux
    generic map
    (
      width => 16
      )
    port map
    (
      i_sig0 => s_l0,
      i_sig1 => rot_1,
      i_sel  => i_s(2),
      o_sig  => s_l1
      );

  -- Second rotation layer
  rot_l2_mux : mux
    generic map
    (
      width => 2
      )
    port map
    (
      i_sig0 => s_2,
      i_sig1 => s_l1(1 downto 0),
      i_sel  => i_rot,
      o_sig  => rot_2(15 downto 14)
      );

  rot_2(13 downto 0) <= s_l1(15 downto 2);

  -- 2-bit shift
  mux_2shift : mux
    generic map
    (
      width => 16
      )
    port map
    (
      i_sig0 => s_l1,
      i_sig1 => rot_2,
      i_sel  => i_s(1),
      o_sig  => s_l2
      );

  -- Third rotation layer
  rot_l3_mux : mux
    generic map
    (
      width => 1
      )
    port map
    (
      i_sig0(0) => s,
      i_sig1(0) => s_l2(0),
      i_sel     => i_rot,
      o_sig(0)  => rot_3(15)
      );

  rot_3(14 downto 0) <= s_l2(15 downto 1);

  -- 1-bit shift
  mux_1shift : mux
    generic map
    (
      width => 16
      )
    port map
    (
      i_sig0 => s_l2(15 downto 0),
      i_sig1 => rot_3(15 downto 0),
      i_sel  => i_s(0),
      o_sig  => s_l3(15 downto 0)
      );

  -- Adjust the sign for arithmetic left shifts
  sign_sl : mux
    generic map
    (
      width => 1
      )
    port map
    (
      i_sig0(0) => s_l3(0),
      i_sig1(0) => rev_0(0),
      i_sel     => sl,
      o_sig(0)  => sign_sig
      );
  adj_s_l3 <= s_l3(15 downto 1) & sign_sig;

  -- Reverse the bit order again
  rev1_mux : mux
    generic map
    (
      width => 16
      )
    port map
    (
      i_sig0 => adj_s_l3(15 downto 0),
      i_sig1 => reverse_vector(s_l3),
      i_sel  => i_dir,
      o_sig  => rev_1(15 downto 0)
      );

  -- Overflow detection
  of0_mux : mux
    generic map
    (
      width => 8
      )
    port map
    (
      i_sig0 => rev_0_8,
      i_sig1 => rev_0(8 downto 1),
      i_sel  => i_s(3),
      o_sig  => of_mux_out0
      );

  of1_mux : mux
    generic map
    (
      width => 4
      )
    port map
    (
      i_sig0 => rev_0_4,
      i_sig1 => s_l0(4 downto 1),
      i_sel  => i_s(2),
      o_sig  => of_mux_out1
      );

  of2_mux : mux
    generic map
    (
      width => 2
      )
    port map
    (
      i_sig0 => rev_0_2,
      i_sig1 => s_l1(2 downto 1),
      i_sel  => i_s(1),
      o_sig  => of_mux_out2
      );

  of3_mux : mux
    generic map
    (
      width => 1
      )
    port map
    (
      i_sig0(0) => rev_0(0),
      i_sig1(0) => s_l2(1),
      i_sel     => i_s(0),
      o_sig(0)  => of_mux_out3
      );

  xor_0 : for i in 0 to 7 generate
    xor_out0(i) <= of_mux_out0(i) xor rev_0_8(i);
  end generate;

  xor_1 : for i in 0 to 3 generate
    xor_out1(i) <= of_mux_out1(i) xor rev_0_4(i);
  end generate;

  xor_2 : for i in 0 to 1 generate
    xor_out2(i) <= of_mux_out2(i) xor rev_0_2(i);
  end generate;

  xor_out3 <= of_mux_out3 xor rev_0(0);

  of_tmp0 <= xor_out0(0) or xor_out0(1) or xor_out0(2) or xor_out0(3)
             or xor_out0(4) or xor_out0(5) or xor_out0(6) or xor_out0(7);
  of_tmp1 <= xor_out1(0) or xor_out1(1) or xor_out1(2) or xor_out1(3);
  of_tmp2 <= xor_out2(0) or xor_out2(1);
  of_tmp3 <= xor_out3;

  sh_f <= sl and (of_tmp0 or of_tmp1 or of_tmp2 or of_tmp3);
  sh_z <= '1' when rev_1 = "0000000000000000" else '0';
  sh_n <= '1' when rev_1(15) = '1' else '0';

  o_flags <= sh_z & sh_f & sh_z & sh_n;
  o_res <= rev_1;
end architecture;

tests/shifter_tb.vhd
library ieee;
use ieee.std_logic_1164.all;

entity shifter_tb is
end shifter_tb;

architecture behaviour of shifter_tb is
  component shifter is
    port
      (
        i_op  : in  std_logic_vector(15 downto 0);
        i_s   : in  std_logic_vector(3 downto 0);
        i_dir : in  std_logic;
        i_rot : in  std_logic;
        i_ar  : in  std_logic;
        o_res : out std_logic_vector(15 downto 0);
        o_flags : out std_logic_vector(3 downto 0)
        );
  end component;

  signal op_tb, r_tb                 : std_logic_vector(15 downto 0);
  signal s_tb                        : std_logic_vector(3 downto 0);
  signal f_tb, dir_tb, rot_tb, ar_tb : std_logic;
  signal flags_tb                    : std_logic_vector(3 downto 0);

begin
  dut : shifter port map
    (
      i_op  => op_tb,
      i_s   => s_tb,
      i_dir => dir_tb,
      i_rot => rot_tb,
      i_ar  => ar_tb,
      o_res  => r_tb,
      o_flags => flags_tb
      );

  stim_proc : process
    type pattern_type is record
      op  : std_logic_vector(15 downto 0);
      s   : std_logic_vector(3 downto 0);
      dir : std_logic;
      rot : std_logic;
      ar  : std_logic;
      r   : std_logic_vector(15 downto 0);
      flags   : std_logic_vector(3 downto 0);
    end record;

    type pattern_array is array(natural range <>) of pattern_type;
    constant patterns : pattern_array :=
      -- left shift
      (("0000000000000001", "0001", '1', '0', '0', "0000000000000010", "0000"),
       ("0000000000000001", "1111", '1', '0', '0', "1000000000000000", "0001"),
       ("0101010101010101", "0001", '1', '0', '0', "1010101010101010", "0001"),
       ("0101010101010101", "0011", '1', '0', '0', "1010101010101000", "0001"),
       ("0000000100000001", "0101", '1', '0', '0', "0010000000100000", "0000"),
       -- left rotate
       ("0000000000000001", "0011", '1', '1', '0', "0000000000001000", "0000"),
       ("0001001010010001", "1011", '1', '1', '0', "1000100010010100", "0001"),
       ("1110000000000001", "0111", '1', '1', '0', "0000000011110000", "0000"),
       ("0000000000000001", "0011", '1', '1', '0', "0000000000001000", "0000"),
       -- left arithmetic shift
       ("0000000000000001", "0001", '1', '0', '1', "0000000000000010", "0000"),
       ("0000000000000001", "1111", '1', '0', '1', "1000000000000000", "0101"),
       ("0000000000000011", "1111", '1', '0', '1', "1000000000000000", "0101"),
       ("0101010101010101", "0001", '1', '0', '1', "1010101010101010", "0101"),
       ("0101010101010101", "0011", '1', '0', '1', "1010101010101000", "0101"),
       ("0000000100000001", "0101", '1', '0', '1', "0010000000100000", "0000"),
       ("0000000100000001", "0111", '1', '0', '1', "1000000010000000", "0101"),
       -- right shift
       ("0000000000000001", "0001", '0', '0', '0', "0000000000000000", "1010"),
       ("0101010101010101", "0001", '0', '0', '0', "0010101010101010", "0000"),
       -- right rotate
       ("1111111111111111", "1111", '0', '1', '0', "1111111111111111", "0001"),
       ("0000000000000001", "0011", '0', '1', '0', "0010000000000000", "0000"),
       ("0001000000000001", "0100", '0', '1', '0', "0001000100000000", "0000"),
       ("0001001010010001", "1011", '0', '1', '0', "0101001000100010", "0000"),
       -- right arithmetic shift
       ("1000000000000001", "0011", '0', '0', '1', "1111000000000000", "0001"),
       ("0000000000000001", "0001", '0', '0', '1', "0000000000000000", "1010"),
       ("0101010101010101", "0001", '0', '0', '1', "0010101010101010", "0000"));

  begin
    for i in patterns'range loop
      op_tb  <= patterns(i).op;
      s_tb   <= patterns(i).s;
      dir_tb <= patterns(i).dir;
      rot_tb <= patterns(i).rot;
      ar_tb  <= patterns(i).ar;
      wait for 1 ns;
      assert r_tb = patterns(i).r report "bad result" severity error;
      assert flags_tb = patterns(i).flags report "bad flag value" severity error;
    end loop;

    assert false report "Shifter testbench finished" severity note;
    wait;
  end process;
end architecture;

sim/shifter_tb.vcd
$date
  Sun May 19 20:49:50 2019
$end
$version
  GHDL v0
$end
$timescale
  1 fs
$end
$scope module standard $end
$upscope $end
$scope module textio $end
$upscope $end
$scope module std_logic_1164 $end
$upscope $end
$scope module numeric_std $end
$upscope $end
$scope module shifter_tb $end
$var reg 16 ! op_tb[15:0] $end
$var reg 16 " r_tb[15:0] $end
$var reg 4 # s_tb[3:0] $end
$var reg 1 $ f_tb $end
$var reg 1 % dir_tb $end
$var reg 1 & rot_tb $end
$var reg 1 ' ar_tb $end
$var reg 4 ( flags_tb[3:0] $end
$scope module dut $end
$var reg 16 ) i_op[15:0] $end
$var reg 4 * i_s[3:0] $end
$var reg 1 + i_dir $end
$var reg 1 , i_rot $end
$var reg 1 - i_ar $end
$var reg 16 . o_res[15:0] $end
$var reg 4 / o_flags[3:0] $end
$var reg 16 0 rev_0[15:0] $end
$var reg 8 1 rev_0_8[7:0] $end
$var reg 4 2 rev_0_4[3:0] $end
$var reg 2 3 rev_0_2[1:0] $end
$var reg 16 4 rev_1[15:0] $end
$var reg 16 5 rot_0[15:0] $end
$var reg 16 6 rot_1[15:0] $end
$var reg 16 7 rot_2[15:0] $end
$var reg 16 8 rot_3[15:0] $end
$var reg 16 9 s_l0[15:0] $end
$var reg 16 : s_l1[15:0] $end
$var reg 16 ; s_l2[15:0] $end
$var reg 16 < s_l3[15:0] $end
$var reg 1 = s $end
$var reg 2 > s_2[1:0] $end
$var reg 4 ? s_4[3:0] $end
$var reg 8 @ s_8[7:0] $end
$var reg 1 A sl $end
$var reg 1 B sr $end
$var reg 1 C sign_sig $end
$var reg 16 D adj_s_l3[15:0] $end
$var reg 8 E of_mux_out0[7:0] $end
$var reg 4 F of_mux_out1[3:0] $end
$var reg 2 G of_mux_out2[1:0] $end
$var reg 1 H of_mux_out3 $end
$var reg 8 I xor_out0[7:0] $end
$var reg 4 J xor_out1[3:0] $end
$var reg 2 K xor_out2[1:0] $end
$var reg 1 L xor_out3 $end
$var reg 1 M of_tmp0 $end
$var reg 1 N of_tmp1 $end
$var reg 1 O of_tmp2 $end
$var reg 1 P of_tmp3 $end
$var reg 1 Q sh_z $end
$var reg 1 R sh_f $end
$var reg 1 S sh_c $end
$var reg 1 T sh_n $end
$scope module rev0_mux $end
$var reg 16 U i_sig0[15:0] $end
$var reg 16 V i_sig1[15:0] $end
$var reg 1 W i_sel $end
$var reg 16 X o_sig[15:0] $end
$upscope $end
$scope module arith_mux $end
$var reg 1 Y i_sig0[0:0] $end
$var reg 1 Z i_sig1[0:0] $end
$var reg 1 [ i_sel $end
$var reg 1 \ o_sig[0:0] $end
$upscope $end
$scope module rot_l0_mux $end
$var reg 8 ] i_sig0[7:0] $end
$var reg 8 ^ i_sig1[7:0] $end
$var reg 1 _ i_sel $end
$var reg 8 ` o_sig[7:0] $end
$upscope $end
$scope module mux_8shift $end
$var reg 16 a i_sig0[15:0] $end
$var reg 16 b i_sig1[15:0] $end
$var reg 1 c i_sel $end
$var reg 16 d o_sig[15:0] $end
$upscope $end
$scope module rot_l1_mux $end
$var reg 4 e i_sig0[3:0] $end
$var reg 4 f i_sig1[3:0] $end
$var reg 1 g i_sel $end
$var reg 4 h o_sig[3:0] $end
$upscope $end
$scope module mux_4shift $end
$var reg 16 i i_sig0[15:0] $end
$var reg 16 j i_sig1[15:0] $end
$var reg 1 k i_sel $end
$var reg 16 l o_sig[15:0] $end
$upscope $end
$scope module rot_l2_mux $end
$var reg 2 m i_sig0[1:0] $end
$var reg 2 n i_sig1[1:0] $end
$var reg 1 o i_sel $end
$var reg 2 p o_sig[1:0] $end
$upscope $end
$scope module mux_2shift $end
$var reg 16 q i_sig0[15:0] $end
$var reg 16 r i_sig1[15:0] $end
$var reg 1 s i_sel $end
$var reg 16 t o_sig[15:0] $end
$upscope $end
$scope module rot_l3_mux $end
$var reg 1 u i_sig0[0:0] $end
$var reg 1 v i_sig1[0:0] $end
$var reg 1 w i_sel $end
$var reg 1 x o_sig[0:0] $end
$upscope $end
$scope module mux_1shift $end
$var reg 16 y i_sig0[15:0] $end
$var reg 16 z i_sig1[15:0] $end
$var reg 1 { i_sel $end
$var reg 16 | o_sig[15:0] $end
$upscope $end
$scope module sign_sl $end
$var reg 1 } i_sig0[0:0] $end
$var reg 1 !" i_sig1[0:0] $end
$var reg 1 "" i_sel $end
$var reg 1 #" o_sig[0:0] $end
$upscope $end
$scope module rev1_mux $end
$var reg 16 $" i_sig0[15:0] $end
$var reg 16 %" i_sig1[15:0] $end
$var reg 1 &" i_sel $end
$var reg 16 '" o_sig[15:0] $end
$upscope $end
$scope module of0_mux $end
$var reg 8 (" i_sig0[7:0] $end
$var reg 8 )" i_sig1[7:0] $end
$var reg 1 *" i_sel $end
$var reg 8 +" o_sig[7:0] $end
$upscope $end
$scope module of1_mux $end
$var reg 4 ," i_sig0[3:0] $end
$var reg 4 -" i_sig1[3:0] $end
$var reg 1 ." i_sel $end
$var reg 4 /" o_sig[3:0] $end
$upscope $end
$scope module of2_mux $end
$var reg 2 0" i_sig0[1:0] $end
$var reg 2 1" i_sig1[1:0] $end
$var reg 1 2" i_sel $end
$var reg 2 3" o_sig[1:0] $end
$upscope $end
$scope module of3_mux $end
$var reg 1 4" i_sig0[0:0] $end
$var reg 1 5" i_sig1[0:0] $end
$var reg 1 6" i_sel $end
$var reg 1 7" o_sig[0:0] $end
$upscope $end
$scope module xor_0(0) $end
$upscope $end
$scope module xor_0(1) $end
$upscope $end
$scope module xor_0(2) $end
$upscope $end
$scope module xor_0(3) $end
$upscope $end
$scope module xor_0(4) $end
$upscope $end
$scope module xor_0(5) $end
$upscope $end
$scope module xor_0(6) $end
$upscope $end
$scope module xor_0(7) $end
$upscope $end
$scope module xor_1(0) $end
$upscope $end
$scope module xor_1(1) $end
$upscope $end
$scope module xor_1(2) $end
$upscope $end
$scope module xor_1(3) $end
$upscope $end
$scope module xor_2(0) $end
$upscope $end
$scope module xor_2(1) $end
$upscope $end
$upscope $end
$upscope $end
$enddefinitions $end
#0
b0000000000000001 !
b0000000000000010 "
b0001 #
U$
1%
0&
0'
b0000 (
b0000000000000001 )
b0001 *
1+
0,
0-
b0000000000000010 .
b0000 /
b1000000000000000 0
b00000000 1
b0000 2
b00 3
b0000000000000010 4
b0000000010000000 5
b0000100000000000 6
b0010000000000000 7
b0100000000000000 8
b1000000000000000 9
b1000000000000000 :
b1000000000000000 ;
b0100000000000000 <
0=
b00 >
b0000 ?
b00000000 @
0A
0B
0C
b0100000000000000 D
b00000000 E
b0000 F
b00 G
0H
b00000000 I
b0000 J
b00 K
0L
0M
0N
0O
0P
0Q
0R
0S
0T
b0000000000000001 U
b1000000000000000 V
1W
b1000000000000000 X
b0 Y
b1 Z
0[
b0 \
b00000000 ]
b00000000 ^
0_
b00000000 `
b1000000000000000 a
b0000000010000000 b
0c
b1000000000000000 d
b0000 e
b0000 f
0g
b0000 h
b1000000000000000 i
b0000100000000000 j
0k
b1000000000000000 l
b00 m
b00 n
0o
b00 p
b1000000000000000 q
b0010000000000000 r
0s
b1000000000000000 t
b0 u
b0 v
0w
b0 x
b1000000000000000 y
b0100000000000000 z
1{
b0100000000000000 |
b0 }
b0 !"
0""
b0 #"
b0100000000000000 $"
b0000000000000010 %"
1&"
b0000000000000010 '"
b00000000 ("
b00000000 )"
0*"
b00000000 +"
b0000 ,"
b0000 -"
0."
b0000 /"
b00 0"
b00 1"
02"
b00 3"
b0 4"
b0 5"
16"
b0 7"
#1000000
b1000000000000000 "
b1111 #
b0001 (
b1111 *
b1000000000000000 .
b0001 /
b1000000000000000 4
b0000000000001000 6
b0000000000000010 7
b0000000000000001 8
b0000000010000000 9
b0000000000001000 :
b0000000000000010 ;
b0000000000000001 <
1C
b0000000000000001 D
1H
1L
1P
1T
1c
b0000000010000000 d
b0000000010000000 i
b0000000000001000 j
1k
b0000000000001000 l
b0000000000001000 q
b0000000000000010 r
1s
b0000000000000010 t
b0000000000000010 y
b0000000000000001 z
b0000000000000001 |
b1 }
b1 #"
b0000000000000001 $"
b1000000000000000 %"
b1000000000000000 '"
1*"
1."
12"
b1 5"
b1 7"
#2000000
b0101010101010101 !
b1010101010101010 "
b0001 #
b0001 (
b0101010101010101 )
b0001 *
b1010101010101010 .
b0001 /
b1010101010101010 0
b1010101010101010 4
b0000000010101010 5
b0000101010101010 6
b0010101010101010 7
b0101010101010101 8
b1010101010101010 9
b1010101010101010 :
b1010101010101010 ;
b0101010101010101 <
1C
b0101010101010101 D
1H
1L
1P
1T
b0101010101010101 U
b1010101010101010 V
b1010101010101010 X
b10101010 ^
b1010101010101010 a
b0000000010101010 b
0c
b1010101010101010 d
b1010 f
b1010101010101010 i
b0000101010101010 j
0k
b1010101010101010 l
b10 n
b1010101010101010 q
b0010101010101010 r
0s
b1010101010101010 t
b1010101010101010 y
b0101010101010101 z
b0101010101010101 |
b1 }
b1 #"
b0101010101010101 $"
b1010101010101010 %"
b1010101010101010 '"
b01010101 )"
0*"
b0101 -"
0."
b01 1"
02"
b1 5"
b1 7"
#3000000
b1010101010101000 "
b0011 #
b0011 *
b1010101010101000 .
b1010101010101000 4
b0001010101010101 8
b0010101010101010 ;
b0001010101010101 <
b0001010101010101 D
b01 G
b01 K
1O
1s
b0010101010101010 t
b0010101010101010 y
b0001010101010101 z
b0001010101010101 |
b0001010101010101 $"
b1010101010101000 %"
b1010101010101000 '"
12"
b01 3"
#4000000
b0000000100000001 !
b0010000000100000 "
b0101 #
b0000 (
b0000000100000001 )
b0101 *
b0010000000100000 .
b0000 /
b1000000010000000 0
b0010000000100000 4
b0000000010000000 5
b0000100000001000 6
b0000001000000010 7
b0000010000000100 8
b1000000010000000 9
b0000100000001000 :
b0000100000001000 ;
b0000010000000100 <
0C
b0000010000000100 D
b0000 F
b00 G
0H
b0000 J
b00 K
0L
0N
0O
0P
0T
b0000000100000001 U
b1000000010000000 V
b1000000010000000 X
b10000000 ^
b1000000010000000 a
b0000000010000000 b
b1000000010000000 d
b0000 f
b1000000010000000 i
b0000100000001000 j
1k
b0000100000001000 l
b00 n
b0000100000001000 q
b0000001000000010 r
0s
b0000100000001000 t
b0000100000001000 y
b0000010000000100 z
b0000010000000100 |
b0 }
b0 #"
b0000010000000100 $"
b0010000000100000 %"
b0010000000100000 '"
b01000000 )"
b0000 -"
1."
b0000 /"
b00 1"
02"
b00 3"
b0 5"
b0 7"
#5000000
b0000000000000001 !
b0000000000001000 "
b0011 #
1&
b0000 (
b0000000000000001 )
b0011 *
1,
b0000000000001000 .
b0000 /
b1000000000000000 0
b0000000000001000 4
b0000000010000000 5
b0000100000000000 6
b0010000000000000 7
b0001000000000000 8
b1000000000000000 9
b1000000000000000 :
b0010000000000000 ;
b0001000000000000 <
0C
b0001000000000000 D
0H
0L
0P
0T
b0000000000000001 U
b1000000000000000 V
b1000000000000000 X
b00000000 ^
1_
b00000000 `
b1000000000000000 a
b0000000010000000 b
b1000000000000000 d
1g
b1000000000000000 i
b0000100000000000 j
0k
b1000000000000000 l
1o
b1000000000000000 q
b0010000000000000 r
1s
b0010000000000000 t
1w
b0010000000000000 y
b0001000000000000 z
b0001000000000000 |
b0 }
b0 #"
b0001000000000000 $"
b0000000000001000 %"
b0000000000001000 '"
b00000000 )"
0."
12"
b0 5"
b0 7"
#6000000
b0001001010010001 !
b1000100010010100 "
b1011 #
b0001 (
b0001001010010001 )
b1011 *
b1000100010010100 .
b0001 /
b1000100101001000 0
b1000100010010100 4
b0100100010001001 5
b1001010010001000 6
b0101001000100010 7
b0010100100010001 8
b0100100010001001 9
b0100100010001001 :
b0101001000100010 ;
b0010100100010001 <
1C
b0010100100010001 D
b10100100 E
1H
b10100100 I
1L
1M
1P
1T
b0001001010010001 U
b1000100101001000 V
b1000100101001000 X
b01001000 ^
b01001000 `
b1000100101001000 a
b0100100010001001 b
1c
b0100100010001001 d
b1001 f
b1001 h
b0100100010001001 i
b1001010010001000 j
b0100100010001001 l
b01 n
b01 p
b0100100010001001 q
b0101001000100010 r
b0101001000100010 t
b0101001000100010 y
b0010100100010001 z
b0010100100010001 |
b1 }
b1 #"
b0010100100010001 $"
b1000100010010100 %"
b1000100010010100 '"
b10100100 )"
1*"
b10100100 +"
b0100 -"
b1 5"
b1 7"
#7000000
b1110000000000001 !
b0000000011110000 "
b0111 #
b0000 (
b1110000000000001 )
b0111 *
b0000000011110000 .
b0000 /
b1000000000000111 0
b11111111 1
b1111 2
b11 3
b0000000011110000 4
b0000011110000000 5
b0111100000000000 6
b0001111000000000 7
b0000111100000000 8
b1000000000000111 9
b0111100000000000 :
b0001111000000000 ;
b0000111100000000 <
0C
b0000111100000000 D
b11111111 E
b0011 F
b00 G
0H
b00000000 I
b1100 J
b11 K
1L
0M
1N
1O
1P
0T
b1110000000000001 U
b1000000000000111 V
b1000000000000111 X
b00000111 ^
b00000111 `
b1000000000000111 a
b0000011110000000 b
0c
b1000000000000111 d
b0111 f
b0111 h
b1000000000000111 i
b0111100000000000 j
1k
b0111100000000000 l
b00 n
b00 p
b0111100000000000 q
b0001111000000000 r
b0001111000000000 t
b0 v
b0 x
b0001111000000000 y
b0000111100000000 z
b0000111100000000 |
b0 }
b1 !"
b0 #"
b0000111100000000 $"
b0000000011110000 %"
b0000000011110000 '"
b11111111 ("
b00000011 )"
0*"
b11111111 +"
b1111 ,"
b0011 -"
1."
b0011 /"
b11 0"
b00 1"
b00 3"
b1 4"
b0 5"
b0 7"
#8000000
b0000000000000001 !
b0000000000001000 "
b0011 #
b0000000000000001 )
b0011 *
b0000000000001000 .
b1000000000000000 0
b00000000 1
b0000 2
b00 3
b0000000000001000 4
b0000000010000000 5
b0000100000000000 6
b0010000000000000 7
b0001000000000000 8
b1000000000000000 9
b1000000000000000 :
b0010000000000000 ;
b0001000000000000 <
b0001000000000000 D
b00000000 E
b0000 F
b00 G
b00000000 I
b0000 J
b00 K
0L
0M
0N
0O
0P
b0000000000000001 U
b1000000000000000 V
b1000000000000000 X
b00000000 ^
b00000000 `
b1000000000000000 a
b0000000010000000 b
b1000000000000000 d
b0000 f
b0000 h
b1000000000000000 i
b0000100000000000 j
0k
b1000000000000000 l
b00 n
b00 p
b1000000000000000 q
b0010000000000000 r
b0010000000000000 t
b0 v
b0 x
b0010000000000000 y
b0001000000000000 z
b0001000000000000 |
b0 !"
b0001000000000000 $"
b0000000000001000 %"
b0000000000001000 '"
b00000000 ("
b00000000 )"
b00000000 +"
b0000 ,"
b0000 -"
0."
b0000 /"
b00 0"
b00 1"
b00 3"
b0 4"
#9000000
b0000000000000010 "
b0001 #
0&
1'
b0001 *
0,
1-
b0000000000000010 .
b0000000000000010 4
b0100000000000000 8
b1000000000000000 ;
b0100000000000000 <
1A
b0100000000000000 D
0_
0g
0o
0s
b1000000000000000 t
0w
b1000000000000000 y
b0100000000000000 z
b0100000000000000 |
1""
b0100000000000000 $"
b0000000000000010 %"
b0000000000000010 '"
02"
#10000000
b1000000000000000 "
b1111 #
b0101 (
b1111 *
b1000000000000000 .
b0101 /
b1000000000000000 4
b0000000000001000 6
b0000000000000010 7
b0000000000000001 8
b0000000010000000 9
b0000000000001000 :
b0000000000000010 ;
b0000000000000001 <
b0000000000000000 D
1H
1L
1P
1R
1T
1c
b0000000010000000 d
b0000000010000000 i
b0000000000001000 j
1k
b0000000000001000 l
b0000000000001000 q
b0000000000000010 r
1s
b0000000000000010 t
b0000000000000010 y
b0000000000000001 z
b0000000000000001 |
b1 }
b0000000000000000 $"
b1000000000000000 %"
b1000000000000000 '"
1*"
1."
12"
b1 5"
b1 7"
#11000000
b0000000000000011 !
b0000000000000011 )
b1100000000000000 0
b0000000011000000 5
b0000000000001100 6
b0000000000000011 7
b0000000011000000 9
b0000000000001100 :
b0000000000000011 ;
b10 G
b10 K
1O
b0000000000000011 U
b1100000000000000 V
b1100000000000000 X
b1100000000000000 a
b0000000011000000 b
b0000000011000000 d
b0000000011000000 i
b0000000000001100 j
b0000000000001100 l
b0000000000001100 q
b0000000000000011 r
b0000000000000011 t
b1 v
b0000000000000011 y
b10 1"
b10 3"
#12000000
b0101010101010101 !
b1010101010101010 "
b0001 #
b0101 (
b0101010101010101 )
b0001 *
b1010101010101010 .
b0101 /
b1010101010101010 0
b1010101010101010 4
b0000000010101010 5
b0000101010101010 6
b0010101010101010 7
b0101010101010101 8
b1010101010101010 9
b1010101010101010 :
b1010101010101010 ;
b0101010101010101 <
b0101010101010100 D
b00 G
1H
b00 K
1L
0O
1P
1R
1T
b0101010101010101 U
b1010101010101010 V
b1010101010101010 X
b10101010 ^
b1010101010101010 a
b0000000010101010 b
0c
b1010101010101010 d
b1010 f
b1010101010101010 i
b0000101010101010 j
0k
b1010101010101010 l
b10 n
b1010101010101010 q
b0010101010101010 r
0s
b1010101010101010 t
b0 v
b1010101010101010 y
b0101010101010101 z
b0101010101010101 |
b1 }
b0101010101010100 $"
b1010101010101010 %"
b1010101010101010 '"
b01010101 )"
0*"
b0101 -"
0."
b01 1"
02"
b00 3"
b1 5"
b1 7"
